yamldataclassconfig/__init__.py
yamldataclassconfig/config.py
yamldataclassconfig/config_property.py
yamldataclassconfig/exceptions.py
yamldataclassconfig/factory.py
yamldataclassconfig/field_processor.py
yamldataclassconfig/nullable.py
yamldataclassconfig/py.typed
yamldataclassconfig/type_defaults.py
yamldataclassconfig/utility.py
yamldataclassconfig/validation.py
yamldataclassconfig-2.0.4.dist-info/licenses/LICENSE
yamldataclassconfig-2.0.4.dist-info/METADATA
yamldataclassconfig-2.0.4.dist-info/WHEEL
yamldataclassconfig-2.0.4.dist-info/top_level.txt
yamldataclassconfig-2.0.4.dist-info/RECORD
